llmake/__init__.py
llmake/__main__.py
llmake/_c_extension.pyi
llmake/cli/__init__.py
llmake/cli/main.py
llmake/py.typed
llmake-0.0.1.dist-info/LICENSE
llmake-0.0.1.dist-info/METADATA
llmake-0.0.1.dist-info/WHEEL
llmake-0.0.1.dist-info/entry_points.txt
llmake-0.0.1.dist-info/RECORD
