Metadata-Version: 2.1
Name: llmake
Version: 0.0.1
Summary: 
Home-page: https://github.com/smy20011/llmake
License: Apache-2.0
Author: smy20011
Requires-Python: >=3.8,<4.0
Classifier: License :: OSI Approved :: Apache Software License
Classifier: Programming Language :: Python :: 3
Classifier: Programming Language :: Python :: 3.8
Classifier: Programming Language :: Python :: 3.9
Classifier: Programming Language :: Python :: 3.10
Classifier: Programming Language :: Python :: 3.11
Classifier: Programming Language :: Python :: 3.12
Requires-Dist: cyclopts (>=2.9.7,<3.0.0)
Requires-Dist: rich (>=10.11.0)
Requires-Dist: typing-extensions (>=4.12.2,<5.0.0)
Project-URL: Repository, https://github.com/smy20011/llmake
